pyemias/__init__.py
pyemias/__version__.py
pyemias/client.py
pyemias/exceptions.py
pyemias/request_builder.py
pyemias/session_manager.py
pyemias/enums/__init__.py
pyemias/enums/emias_urls.py
pyemias/enums/speciality.py
pyemias/models/__init__.py
pyemias/models/auth_model.py
pyemias/models/emc_response_model.py
pyemias-0.0.4.dist-info/LICENSE
pyemias-0.0.4.dist-info/METADATA
pyemias-0.0.4.dist-info/WHEEL
pyemias-0.0.4.dist-info/top_level.txt
pyemias-0.0.4.dist-info/RECORD
