Metadata-Version: 2.2
Name: pyemias
Version: 0.0.4
Summary: pyemias
Home-page: https://github.com/GvozdevAD/pyemias
Author: GvozdevAD
Author-email: alexander@gvozdev.net
Keywords: emias pyemias
Classifier: Programming Language :: Python :: 3 :: Only
Classifier: Programming Language :: Python :: 3.10
Classifier: Programming Language :: Python :: 3.11
Classifier: License :: OSI Approved :: MIT License
Classifier: Operating System :: OS Independent
Requires-Python: >=3.10
License-File: LICENSE
Requires-Dist: beautifulsoup4==4.12.3
Requires-Dist: certifi==2024.12.14
Requires-Dist: charset-normalizer==3.4.1
Requires-Dist: idna==3.10
Requires-Dist: lxml==5.3.0
Requires-Dist: nanoid==2.0.0
Requires-Dist: requests==2.32.3
Requires-Dist: soupsieve==2.6
Requires-Dist: urllib3==2.3.0
Requires-Dist: pydantic==2.10.6
Dynamic: author
Dynamic: author-email
Dynamic: classifier
Dynamic: description
Dynamic: description-content-type
Dynamic: home-page
Dynamic: keywords
Dynamic: requires-dist
Dynamic: requires-python
Dynamic: summary
